python_sureshmnv/__init__.py
python_sureshmnv/logging_sureshmnv.py
python_sureshmnv/sample.py
python_sureshmnv/subprocess_sureshmnv.py
python_sureshmnv-0.5.0.dist-info/LICENSE
python_sureshmnv-0.5.0.dist-info/METADATA
python_sureshmnv-0.5.0.dist-info/WHEEL
python_sureshmnv-0.5.0.dist-info/top_level.txt
python_sureshmnv-0.5.0.dist-info/RECORD
