Metadata-Version: 2.1
Name: python-sureshmnv
Version: 0.5.0
Summary: Additional wrappers for basic python installation
Home-page: https://github.com/sureshmnv/python_sureshmnv
Author: Suresh Melam
Author-email: sureshmnv@yahoo.com
License: MIT
Platform: UNKNOWN
Classifier: Development Status :: 2 - Pre-Alpha
Classifier: License :: OSI Approved :: MIT License
Classifier: Programming Language :: Python
Classifier: Programming Language :: Python :: 3
Classifier: Programming Language :: Python :: 3.4
Classifier: Programming Language :: Python :: 3.5
Classifier: Programming Language :: Python :: 3.6
Classifier: Programming Language :: Python :: 3.7
